aviary/envs/hotpotqa/__init__.py
aviary/envs/hotpotqa/env.py
aviary/envs/hotpotqa/py.typed
aviary/envs/hotpotqa/version.py
aviary_hotpotqa-0.32.0.dist-info/METADATA
aviary_hotpotqa-0.32.0.dist-info/WHEEL
aviary_hotpotqa-0.32.0.dist-info/top_level.txt
aviary_hotpotqa-0.32.0.dist-info/RECORD
