Metadata-Version: 2.4
Name: aviary.hotpotqa
Version: 0.32.0
Summary: HotPotQA environment implemented with aviary
Author-email: FutureHouse technical staff <hello@futurehouse.org>
Classifier: Intended Audience :: Developers
Classifier: License :: OSI Approved :: Apache Software License
Classifier: Operating System :: OS Independent
Classifier: Programming Language :: Python :: 3 :: Only
Classifier: Programming Language :: Python :: 3.11
Classifier: Programming Language :: Python :: 3.12
Classifier: Programming Language :: Python :: 3.13
Classifier: Programming Language :: Python :: 3.14
Classifier: Programming Language :: Python
Classifier: Topic :: Scientific/Engineering :: Artificial Intelligence
Requires-Python: >=3.11
Requires-Dist: beautifulsoup4
Requires-Dist: datasets>=2.15
Requires-Dist: fhaviary
Requires-Dist: httpx
Requires-Dist: httpx-aiohttp
Requires-Dist: pydantic~=2.0
Requires-Dist: tenacity
